Metadata-Version: 2.1
Name: rockit-meco
Version: 0.6.6
Summary: Rapid Optimal Control Kit
Author-email: MECO-Group <joris.gillis@kuleuven.be>
License: GNU LESSER GENERAL PUBLIC LICENSE
Project-URL: Homepage, https://gitlab.kuleuven.be/meco-software/rockit
Keywords: OCP,optimal control,casadi
Classifier: Development Status :: 3 - Alpha
Classifier: License :: OSI Approved :: GNU Lesser General Public License v3 (LGPLv3)
Classifier: Programming Language :: Python :: 3
Classifier: Topic :: Scientific/Engineering
Requires-Python: >=3.6
License-File: LICENSE
Requires-Dist: casadi <4.0,>=3.5
Requires-Dist: numpy
Requires-Dist: matplotlib
Requires-Dist: scipy
Requires-Dist: future-fstrings
